pykda/KDA.py
pykda/Markov_chain.py
pykda/__init__.py
pykda/constants.py
pykda/data/Courtois_matrix.csv
pykda/data/Lord_of_the_Rings.csv
pykda/data/Moreno_social_network.csv
pykda/data/README.md
pykda/data/Zacharys_karate_club.csv
pykda/data/land_of_Oz.csv
pykda/data/primary_school_network.csv
pykda/loaders.py
pykda/normalizers.py
pykda/utilities.py
pykda-0.9.3.dist-info/LICENSE.md
pykda-0.9.3.dist-info/METADATA
pykda-0.9.3.dist-info/WHEEL
pykda-0.9.3.dist-info/RECORD
