Metadata-Version: 2.1
Name: pykda
Version: 0.9.3
Summary: Python package for the Kemeny Decomposition Algorithm (KDA) together with some Markov chain tooling.
Home-page: https://github.com/JoostBerkhout/PyKDA
License: MIT
Keywords: Markov chain,Kemeny Decomposition Algorithm,KDA,Kemeny constant
Author: Joost Berkhout
Author-email: joost.berkhout@vu.nl
Maintainer: Joost Berkhout
Maintainer-email: joost.berkhout@vu.nl
Requires-Python: >=3.10,<4.0
Classifier: License :: OSI Approved :: MIT License
Classifier: Programming Language :: Python :: 3
Classifier: Programming Language :: Python :: 3.10
Classifier: Programming Language :: Python :: 3.11
Classifier: Programming Language :: Python :: 3.12
Requires-Dist: numpy (>=1.26.4,<2.0.0)
Requires-Dist: pyvis (>=0.3.2,<0.4.0)
Requires-Dist: tarjan (>=0.2.4,<0.3.0)
Project-URL: Documentation, https://joostberkhout.github.io/PyKDA/
Project-URL: Repository, https://github.com/JoostBerkhout/PyKDA
